Helicity_Computation_Crystals.py
__init__.py
Helicity_Computation_Crystals-0.0.7.dist-info/LICENSE
Helicity_Computation_Crystals-0.0.7.dist-info/METADATA
Helicity_Computation_Crystals-0.0.7.dist-info/WHEEL
Helicity_Computation_Crystals-0.0.7.dist-info/entry_points.txt
Helicity_Computation_Crystals-0.0.7.dist-info/top_level.txt
Helicity_Computation_Crystals-0.0.7.dist-info/RECORD
